{
	"name": "trigger_alert",
	"properties": {
		"annotations": [],
		"runtimeState": "Started",
		"pipelines": [
			{
				"pipelineReference": {
					"referenceName": "Copy_data",
					"type": "PipelineReference"
				},
				"parameters": {
					"input_file_name": "12",
					"output_file_name": "1111"
				}
			}
		],
		"type": "ScheduleTrigger",
		"typeProperties": {
			"recurrence": {
				"frequency": "Minute",
				"interval": 1,
				"startTime": "2022-11-29T17:07:00Z",
				"timeZone": "UTC"
			}
		}
	}
}